mdsb/__init__.py
mdsb/main.py
mdsb-0.0.1.dist-info/METADATA
mdsb-0.0.1.dist-info/WHEEL
mdsb-0.0.1.dist-info/entry_points.txt
mdsb-0.0.1.dist-info/licenses/LICENSE
mdsb-0.0.1.dist-info/RECORD
